kagescope/__init__.py
kagescope/cli.py
kagescope/core.py
kagescope/ui.py
kagescope/utils.py
kagescope-2.0.3.dist-info/METADATA
kagescope-2.0.3.dist-info/WHEEL
kagescope-2.0.3.dist-info/entry_points.txt
kagescope-2.0.3.dist-info/top_level.txt
kagescope-2.0.3.dist-info/RECORD
