Metadata-Version: 2.4
Name: kagescope
Version: 2.0.3
Summary: Low-noise recon tool for bug bounty and security research
Requires-Python: >=3.9
Requires-Dist: rich>=13.7.0
